newgrab.py
newgrabmod.py
grab_reddit-0.0.8.dist-info/LICENSE
grab_reddit-0.0.8.dist-info/METADATA
grab_reddit-0.0.8.dist-info/WHEEL
grab_reddit-0.0.8.dist-info/entry_points.txt
grab_reddit-0.0.8.dist-info/top_level.txt
grab_reddit-0.0.8.dist-info/RECORD
