Metadata-Version: 2.1
Name: grab-reddit
Version: 0.0.8
Summary: A Reddit download bot
Home-page: https://gitlab.com/RealStickman/grab/
Author: RealStickman
Author-email: mrcfrm01@protonmail.com
License: UNKNOWN
Platform: UNKNOWN
Classifier: Natural Language :: English
Classifier: Programming Language :: Python :: 3
Classifier: Programming Language :: Python :: 3.7
Classifier: Programming Language :: Python :: 3.8
Classifier: Programming Language :: Python :: 3.9
Classifier: License :: OSI Approved :: BSD License
Classifier: Operating System :: POSIX :: Linux
Classifier: Development Status :: 3 - Alpha
License-File: LICENSE
Requires-Dist: praw (>=7.1.0)
Provides-Extra: dev
